haystack_hybrid_embedding/__init__.py
haystack_hybrid_embedding/pinecone/__init__.py
haystack_hybrid_embedding/pinecone/mixin.py
haystack_hybrid_embedding/pinecone/proxies.py
haystack_hybrid_embedding/pinecone/retrievers.py
haystack_hybrid_embedding/vector.py
haystack_hybrid_embedding-0.1.0.dist-info/METADATA
haystack_hybrid_embedding-0.1.0.dist-info/WHEEL
haystack_hybrid_embedding-0.1.0.dist-info/RECORD
