Metadata-Version: 2.1
Name: haystack-hybrid-embedding
Version: 0.1.0
Summary: Sparse-Dense Embeddings for Pinecone in Haystack
License: MIT
Author: Yasyf Mohamedali
Author-email: yasyfm@gmail.com
Requires-Python: >=3.9,<4.0
Classifier: License :: OSI Approved :: MIT License
Classifier: Programming Language :: Python :: 3
Classifier: Programming Language :: Python :: 3.9
Classifier: Programming Language :: Python :: 3.10
Classifier: Programming Language :: Python :: 3.11
Requires-Dist: farm-haystack (>=1.17.2,<2.0.0)
Requires-Dist: numpy (>=1.25.0,<2.0.0)
Requires-Dist: pinecone-client (>=2.2.2,<3.0.0)
Requires-Dist: pinecone-text (>=0.5.2,<0.6.0)
Requires-Dist: torch (>=2.0.1,<3.0.0)
Requires-Dist: wrapt (>=1.15.0,<2.0.0)
